TGYUI.kpf
setup.py
TGYUI/__init__.py
TGYUI/release.py
TGYUI/util.py
TGYUI/widgets.py
TGYUI.egg-info/PKG-INFO
TGYUI.egg-info/SOURCES.txt
TGYUI.egg-info/dependency_links.txt
TGYUI.egg-info/entry_points.txt
TGYUI.egg-info/not-zip-safe
TGYUI.egg-info/paster_plugins.txt
TGYUI.egg-info/requires.txt
TGYUI.egg-info/sqlobject.txt
TGYUI.egg-info/top_level.txt
TGYUI/static/yui/license.txt
TGYUI/static/yui/animation/animation-min.js
TGYUI/static/yui/assets/skins/sam/asc.gif
TGYUI/static/yui/assets/skins/sam/autocomplete.css
TGYUI/static/yui/assets/skins/sam/blankimage.png
TGYUI/static/yui/assets/skins/sam/button.css
TGYUI/static/yui/assets/skins/sam/calendar.css
TGYUI/static/yui/assets/skins/sam/colorpicker.css
TGYUI/static/yui/assets/skins/sam/container.css
TGYUI/static/yui/assets/skins/sam/datatable.css
TGYUI/static/yui/assets/skins/sam/desc.gif
TGYUI/static/yui/assets/skins/sam/dt-arrow-dn.png
TGYUI/static/yui/assets/skins/sam/dt-arrow-up.png
TGYUI/static/yui/assets/skins/sam/editor-knob.gif
TGYUI/static/yui/assets/skins/sam/editor-sprite-active.gif
TGYUI/static/yui/assets/skins/sam/editor-sprite.gif
TGYUI/static/yui/assets/skins/sam/editor.css
TGYUI/static/yui/assets/skins/sam/header_background.png
TGYUI/static/yui/assets/skins/sam/hue_bg.png
TGYUI/static/yui/assets/skins/sam/imagecropper.css
TGYUI/static/yui/assets/skins/sam/layout.css
TGYUI/static/yui/assets/skins/sam/layout_sprite.png
TGYUI/static/yui/assets/skins/sam/logger.css
TGYUI/static/yui/assets/skins/sam/menu-button-arrow-disabled.png
TGYUI/static/yui/assets/skins/sam/menu-button-arrow.png
TGYUI/static/yui/assets/skins/sam/menu.css
TGYUI/static/yui/assets/skins/sam/menubaritem_submenuindicator.png
TGYUI/static/yui/assets/skins/sam/menubaritem_submenuindicator_disabled.png
TGYUI/static/yui/assets/skins/sam/menuitem_checkbox.png
TGYUI/static/yui/assets/skins/sam/menuitem_checkbox_disabled.png
TGYUI/static/yui/assets/skins/sam/menuitem_submenuindicator.png
TGYUI/static/yui/assets/skins/sam/menuitem_submenuindicator_disabled.png
TGYUI/static/yui/assets/skins/sam/picker_mask.png
TGYUI/static/yui/assets/skins/sam/profilerviewer.css
TGYUI/static/yui/assets/skins/sam/resize.css
TGYUI/static/yui/assets/skins/sam/simpleeditor.css
