Metadata-Version: 1.0
Name: TGYUI
Version: 2.5.0
Summary: The Yahoo! YUI packaged as collection of TurboGears widgets.
Home-page: http://tgwidgets.ossdl.de/
Author: W-Mark Kubacki, Marco Mariani, Lulamile Mzamo
Author-email: wmark.tgyui@hurrikane.de
License: BSD
Download-URL: http://static.ossdl.de/tgwidgets/downloads/
Keywords: turbogears.widgets
Platform: UNKNOWN
Classifier: Development Status :: 4 - Beta
Classifier: Operating System :: OS Independent
Classifier: Programming Language :: Python
Classifier: Programming Language :: JavaScript
Classifier: Topic :: Software Development :: Libraries :: Python Modules
Classifier: Framework :: TurboGears
Classifier: Framework :: TurboGears :: Widgets
Classifier: License :: OSI Approved :: BSD License
